{"time/epoch": 0, "_timestamp": 1712282794.8360155, "time/batch": 194, "time/sample": 49664, "time/batch_in_epoch": 194, "time/sample_in_epoch": 49664, "trainer/device_train_microbatch_size": 256, "loss/train/total": 0.004119956865906715, "metrics/train/MulticlassAccuracy": 1.0, "_runtime": 19.02050542831421, "_step": 275, "lr-DecoupledAdamW/group0": 1.1176923076923076e-05, "l2_norm/moment/network.bn1.weight": 0.0025535891763865948, "l2_norm/param/network.bn1.weight": 1.1189466714859009, "l2_norm/update/network.bn1.weight": 0.0003204582317266613, "l2_norm/grad/network.bn1.weight": 0.010738394223153591, "l2_norm/moment/network.bn1.bias": 0.002404955215752125, "l2_norm/param/network.bn1.bias": 0.9478544592857361, "l2_norm/update/network.bn1.bias": 0.0002660859900061041, "l2_norm/grad/network.bn1.bias": 0.007690731901675463, "l2_norm/moment/network.layer1.0.bn1.weight": 0.0026714070700109005, "l2_norm/param/network.layer1.0.bn1.weight": 1.1576577425003052, "l2_norm/update/network.layer1.0.bn1.weight": 0.0003284492122475058, "l2_norm/grad/network.layer1.0.bn1.weight": 0.005611810367554426, "l2_norm/moment/network.layer1.0.bn1.bias": 0.001901345793157816, "l2_norm/param/network.layer1.0.bn1.bias": 0.6937156319618225, "l2_norm/update/network.layer1.0.bn1.bias": 0.0002052348427241668, "l2_norm/grad/network.layer1.0.bn1.bias": 0.005063239485025406, "l2_norm/moment/network.layer1.0.bn2.weight": 0.0021791469771414995, "l2_norm/param/network.layer1.0.bn2.weight": 1.4116204977035522, "l2_norm/update/network.layer1.0.bn2.weight": 0.0004058553313370794, "l2_norm/grad/network.layer1.0.bn2.weight": 0.007390064187347889, "l2_norm/moment/network.layer1.0.bn2.bias": 0.001686236122623086, "l2_norm/param/network.layer1.0.bn2.bias": 0.7248510718345642, "l2_norm/update/network.layer1.0.bn2.bias": 0.0002121889847330749, "l2_norm/grad/network.layer1.0.bn2.bias": 0.00488930381834507, "l2_norm/moment/network.layer1.1.bn1.weight": 0.003062391420826316, "l2_norm/param/network.layer1.1.bn1.weight": 1.420064091682434, "l2_norm/update/network.layer1.1.bn1.weight": 0.00040607055416330695, "l2_norm/grad/network.layer1.1.bn1.weight": 0.006950446870177984, "l2_norm/moment/network.layer1.1.bn1.bias": 0.0021902236621826887, "l2_norm/param/network.layer1.1.bn1.bias": 0.6146398782730103, "l2_norm/update/network.layer1.1.bn1.bias": 0.00017826590919867158, "l2_norm/grad/network.layer1.1.bn1.bias": 0.004884025081992149, "l2_norm/moment/network.layer1.1.bn2.weight": 0.002241950947791338, "l2_norm/param/network.layer1.1.bn2.weight": 1.3295758962631226, "l2_norm/update/network.layer1.1.bn2.weight": 0.00038176338421180844, "l2_norm/grad/network.layer1.1.bn2.weight": 0.009013147093355656, "l2_norm/moment/network.layer1.1.bn2.bias": 0.0015806802548468113, "l2_norm/param/network.layer1.1.bn2.bias": 0.9086127281188965, "l2_norm/update/network.layer1.1.bn2.bias": 0.0002635107666719705, "l2_norm/grad/network.layer1.1.bn2.bias": 0.004767381586134434, "l2_norm/moment/network.layer2.0.bn1.weight": 0.0032286106143146753, "l2_norm/param/network.layer2.0.bn1.weight": 1.644620418548584, "l2_norm/update/network.layer2.0.bn1.weight": 0.00047370753600262105, "l2_norm/grad/network.layer2.0.bn1.weight": 0.01197037287056446, "l2_norm/moment/network.layer2.0.bn1.bias": 0.0023520083632320166, "l2_norm/param/network.layer2.0.bn1.bias": 0.7580036520957947, "l2_norm/update/network.layer2.0.bn1.bias": 0.00021823545102961361, "l2_norm/grad/network.layer2.0.bn1.bias": 0.006922096014022827, "l2_norm/moment/network.layer2.0.bn2.weight": 0.0036750021390616894, "l2_norm/param/network.layer2.0.bn2.weight": 1.9446122646331787, "l2_norm/update/network.layer2.0.bn2.weight": 0.0005569107015617192, "l2_norm/grad/network.layer2.0.bn2.weight": 0.010405209846794605, "l2_norm/moment/network.layer2.0.bn2.bias": 0.002366195898503065, "l2_norm/param/network.layer2.0.bn2.bias": 0.6707875728607178, "l2_norm/update/network.layer2.0.bn2.bias": 0.0001925024262163788, "l2_norm/grad/network.layer2.0.bn2.bias": 0.006089548114687204, "l2_norm/moment/network.layer2.0.downsample.1.weight": 0.002977581461891532, "l2_norm/param/network.layer2.0.downsample.1.weight": 1.4226064682006836, "l2_norm/update/network.layer2.0.downsample.1.weight": 0.0004108149150852114, "l2_norm/grad/network.layer2.0.downsample.1.weight": 0.008856608532369137, "l2_norm/moment/network.layer2.0.downsample.1.bias": 0.002366195898503065, "l2_norm/param/network.layer2.0.downsample.1.bias": 0.6707875728607178, "l2_norm/update/network.layer2.0.downsample.1.bias": 0.0001925024262163788, "l2_norm/grad/network.layer2.0.downsample.1.bias": 0.006089548114687204, "l2_norm/moment/network.layer2.1.bn1.weight": 0.004346876870840788, "l2_norm/param/network.layer2.1.bn1.weight": 1.6143494844436646, "l2_norm/update/network.layer2.1.bn1.weight": 0.000463873177068308, "l2_norm/grad/network.layer2.1.bn1.weight": 0.011633798480033875, "l2_norm/moment/network.layer2.1.bn1.bias": 0.0025681552942842245, "l2_norm/param/network.layer2.1.bn1.bias": 1.410386562347412, "l2_norm/update/network.layer2.1.bn1.bias": 0.00040515096043236554, "l2_norm/grad/network.layer2.1.bn1.bias": 0.006092618685215712, "l2_norm/moment/network.layer2.1.bn2.weight": 0.0029170173220336437, "l2_norm/param/network.layer2.1.bn2.weight": 1.4841282367706299, "l2_norm/update/network.layer2.1.bn2.weight": 0.00042673107236623764, "l2_norm/grad/network.layer2.1.bn2.weight": 0.00648938212543726, "l2_norm/moment/network.layer2.1.bn2.bias": 0.001878078910522163, "l2_norm/param/network.layer2.1.bn2.bias": 0.9213815927505493, "l2_norm/update/network.layer2.1.bn2.bias": 0.0002628376823849976, "l2_norm/grad/network.layer2.1.bn2.bias": 0.004578568506985903, "l2_norm/moment/network.layer3.0.bn1.weight": 0.004689638968557119, "l2_norm/param/network.layer3.0.bn1.weight": 2.2622342109680176, "l2_norm/update/network.layer3.0.bn1.weight": 0.0006492533721029758, "l2_norm/grad/network.layer3.0.bn1.weight": 0.01290710736066103, "l2_norm/moment/network.layer3.0.bn1.bias": 0.002909828443080187, "l2_norm/param/network.layer3.0.bn1.bias": 1.3314452171325684, "l2_norm/update/network.layer3.0.bn1.bias": 0.00038108768058009446, "l2_norm/grad/network.layer3.0.bn1.bias": 0.008209175430238247, "l2_norm/moment/network.layer3.0.bn2.weight": 0.006398986559361219, "l2_norm/param/network.layer3.0.bn2.weight": 2.5546135902404785, "l2_norm/update/network.layer3.0.bn2.weight": 0.0007293723756447434, "l2_norm/grad/network.layer3.0.bn2.weight": 0.018272146582603455, "l2_norm/moment/network.layer3.0.bn2.bias": 0.003367913421243429, "l2_norm/param/network.layer3.0.bn2.bias": 1.405227780342102, "l2_norm/update/network.layer3.0.bn2.bias": 0.00040834248648025095, "l2_norm/grad/network.layer3.0.bn2.bias": 0.011194492690265179, "l2_norm/moment/network.layer3.0.downsample.1.weight": 0.004315635189414024, "l2_norm/param/network.layer3.0.downsample.1.weight": 0.9326937794685364, "l2_norm/update/network.layer3.0.downsample.1.weight": 0.00026371152489446104, "l2_norm/grad/network.layer3.0.downsample.1.weight": 0.014063998125493526, "l2_norm/moment/network.layer3.0.downsample.1.bias": 0.003367913421243429, "l2_norm/param/network.layer3.0.downsample.1.bias": 1.405227780342102, "l2_norm/update/network.layer3.0.downsample.1.bias": 0.00040834248648025095, "l2_norm/grad/network.layer3.0.downsample.1.bias": 0.011194492690265179, "l2_norm/moment/network.layer3.1.bn1.weight": 0.006704558152705431, "l2_norm/param/network.layer3.1.bn1.weight": 2.183568000793457, "l2_norm/update/network.layer3.1.bn1.weight": 0.0006269044242799282, "l2_norm/grad/network.layer3.1.bn1.weight": 0.01998133584856987, "l2_norm/moment/network.layer3.1.bn1.bias": 0.003610450541600585, "l2_norm/param/network.layer3.1.bn1.bias": 2.0845656394958496, "l2_norm/update/network.layer3.1.bn1.bias": 0.0005985562456771731, "l2_norm/grad/network.layer3.1.bn1.bias": 0.012269522063434124, "l2_norm/moment/network.layer3.1.bn2.weight": 0.0036012809723615646, "l2_norm/param/network.layer3.1.bn2.weight": 1.9890248775482178, "l2_norm/update/network.layer3.1.bn2.weight": 0.0005746971582993865, "l2_norm/grad/network.layer3.1.bn2.weight": 0.009514872916042805, "l2_norm/moment/network.layer3.1.bn2.bias": 0.0021462985314428806, "l2_norm/param/network.layer3.1.bn2.bias": 1.6425899267196655, "l2_norm/update/network.layer3.1.bn2.bias": 0.0004774075641762465, "l2_norm/grad/network.layer3.1.bn2.bias": 0.006797216832637787, "l2_norm/moment/network.layer4.0.bn1.weight": 0.003337111556902528, "l2_norm/param/network.layer4.0.bn1.weight": 1.4570612907409668, "l2_norm/update/network.layer4.0.bn1.weight": 0.00041983043774962425, "l2_norm/grad/network.layer4.0.bn1.weight": 0.008775554597377777, "l2_norm/moment/network.layer4.0.bn1.bias": 0.0022179039660841227, "l2_norm/param/network.layer4.0.bn1.bias": 1.0052564144134521, "l2_norm/update/network.layer4.0.bn1.bias": 0.0002945851592812687, "l2_norm/grad/network.layer4.0.bn1.bias": 0.007165473885834217, "l2_norm/moment/network.layer4.0.bn2.weight": 0.001485829008743167, "l2_norm/param/network.layer4.0.bn2.weight": 3.9677188396453857, "l2_norm/update/network.layer4.0.bn2.weight": 0.0013068702537566423, "l2_norm/grad/network.layer4.0.bn2.weight": 0.0018790744943544269, "l2_norm/moment/network.layer4.0.bn2.bias": 0.0006359431426972151, "l2_norm/param/network.layer4.0.bn2.bias": 0.654819130897522, "l2_norm/update/network.layer4.0.bn2.bias": 0.0002308770635863766, "l2_norm/grad/network.layer4.0.bn2.bias": 0.0017082829726859927, "l2_norm/moment/network.layer4.0.downsample.1.weight": 0.000528079632204026, "l2_norm/param/network.layer4.0.downsample.1.weight": 1.9307036399841309, "l2_norm/update/network.layer4.0.downsample.1.weight": 0.0006235740729607642, "l2_norm/grad/network.layer4.0.downsample.1.weight": 0.0011654678964987397, "l2_norm/moment/network.layer4.0.downsample.1.bias": 0.0006359431426972151, "l2_norm/param/network.layer4.0.downsample.1.bias": 0.654819130897522, "l2_norm/update/network.layer4.0.downsample.1.bias": 0.0002308770635863766, "l2_norm/grad/network.layer4.0.downsample.1.bias": 0.0017082829726859927, "l2_norm/moment/network.layer4.1.bn1.weight": 0.0010798382572829723, "l2_norm/param/network.layer4.1.bn1.weight": 0.9043703675270081, "l2_norm/update/network.layer4.1.bn1.weight": 0.0002834320766851306, "l2_norm/grad/network.layer4.1.bn1.weight": 0.002274177735671401, "l2_norm/moment/network.layer4.1.bn1.bias": 0.001512573566287756, "l2_norm/param/network.layer4.1.bn1.bias": 0.17396514117717743, "l2_norm/update/network.layer4.1.bn1.bias": 7.466464739991352e-05, "l2_norm/grad/network.layer4.1.bn1.bias": 0.0030090922955423594, "l2_norm/moment/network.layer4.1.bn2.weight": 0.002356755081564188, "l2_norm/param/network.layer4.1.bn2.weight": 3.1535322666168213, "l2_norm/update/network.layer4.1.bn2.weight": 0.0011102586286142468, "l2_norm/grad/network.layer4.1.bn2.weight": 0.0027943463064730167, "l2_norm/moment/network.layer4.1.bn2.bias": 0.0008733090944588184, "l2_norm/param/network.layer4.1.bn2.bias": 0.8929305076599121, "l2_norm/update/network.layer4.1.bn2.bias": 0.00034137096372433007, "l2_norm/grad/network.layer4.1.bn2.bias": 0.0015972607070580125, "l2_norm/moment/network.fc.weight": 0.002978587755933404, "l2_norm/param/network.fc.weight": 5.745650291442871, "l2_norm/update/network.fc.weight": 0.0019400407327339053, "l2_norm/grad/network.fc.weight": 0.005490804091095924, "l2_norm/moment/network.fc.bias": 0.0001795112038962543, "l2_norm/param/network.fc.bias": 0.09934745728969574, "l2_norm/update/network.fc.bias": 2.815126754285302e-05, "l2_norm/grad/network.fc.bias": 0.0007580192177556455, "l2_norm/grad/global": 0.05541713163256645, "network.conv1_mu": {"_type": "histogram", "values": [1, 0, 0, 1, 2, 0, 0, 0, 0, 0, 0, 0, 0, 0, 0, 0, 0, 1, 0, 0, 0, 0, 0, 0, 1, 0, 0, 0, 0, 0, 0, 0, 0, 0, 0, 0, 0, 0, 1, 0, 0, 0, 1, 1, 0, 1, 1, 0, 0, 1, 1, 0, 0, 0, 0, 0, 0, 0, 1, 0, 0, 0, 0, 1], "bins": [0.0983496904373169, 0.1106855571269989, 0.12302142381668091, 0.13535729050636292, 0.14769315719604492, 0.16002902388572693, 0.17236489057540894, 0.18470075726509094, 0.19703662395477295, 0.20937249064445496, 0.22170835733413696, 0.23404422402381897, 0.24638009071350098, 0.258715957403183, 0.271051824092865, 0.283387690782547, 0.295723557472229, 0.308059424161911, 0.320395290851593, 0.332731157541275, 0.34506702423095703, 0.35740289092063904, 0.36973875761032104, 0.38207462430000305, 0.39441049098968506, 0.40674635767936707, 0.4190822243690491, 0.4314180910587311, 0.4437539577484131, 0.4560898244380951, 0.4684256911277771, 0.4807615578174591, 0.4930974245071411, 0.5054333209991455, 0.5177691578865051, 0.5301049947738647, 0.5424408912658691, 0.5547767877578735, 0.5671126246452332, 0.5794484615325928, 0.5917843580245972, 0.6041202545166016, 0.6164560914039612, 0.6287919282913208, 0.6411278247833252, 0.6534637212753296, 0.6657995581626892, 0.6781353950500488, 0.6904712915420532, 0.7028071880340576, 0.7151430249214172, 0.7274788618087769, 0.7398147583007812, 0.7521506547927856, 0.7644864916801453, 0.7768223285675049, 0.7891582250595093, 0.8014941215515137, 0.8138299584388733, 0.8261657953262329, 0.8385016918182373, 0.8508375883102417, 0.8631734251976013, 0.8755092620849609, 0.8878451585769653]}, "network.conv1_P_zeros": 0.6157407407407407, "network.conv1_S_zeros": 0.0, "network.conv1_Origin_zeros": 0.0, "network.layer1.0.conv1_mu": {"_type": "histogram", "values": [2, 0, 1, 0, 0, 0, 0, 1, 0, 0, 0, 0, 0, 0, 1, 0, 2, 0, 1, 1, 1, 0, 0, 0, 0, 0, 0, 0, 0, 0, 0, 0, 0, 1, 0, 0, 0, 0, 0, 0, 0, 0, 0, 1, 1, 0, 0, 0, 1, 0, 0, 0, 0, 0, 0, 0, 0, 0, 0, 0, 0, 0, 0, 1], "bins": [0.035102248191833496, 0.04747895896434784, 0.059855666011571884, 0.07223237305879593, 0.08460908383131027, 0.09698579460382462, 0.10936249792575836, 0.1217392086982727, 0.13411591947078705, 0.1464926302433014, 0.15886934101581573, 0.17124605178833008, 0.18362274765968323, 0.19599945843219757, 0.20837616920471191, 0.22075287997722626, 0.2331295907497406, 0.24550630152225494, 0.2578830122947693, 0.27025970816612244, 0.282636433839798, 0.2950131297111511, 0.30738985538482666, 0.3197665512561798, 0.33214324712753296, 0.3445199728012085, 0.35689666867256165, 0.3692733943462372, 0.38165009021759033, 0.39402681589126587, 0.406403511762619, 0.41878023743629456, 0.4311569333076477, 0.44353362917900085, 0.4559103548526764, 0.46828705072402954, 0.4806637763977051, 0.4930404722690582, 0.5054171681404114, 0.5177938938140869, 0.5301706194877625, 0.5425472855567932, 0.5549240112304688, 0.5673007369041443, 0.5796774625778198, 0.5920541286468506, 0.6044308543205261, 0.6168075799942017, 0.6291842460632324, 0.641560971736908, 0.6539376974105835, 0.666314423084259, 0.6786910891532898, 0.6910678148269653, 0.7034445405006409, 0.7158212661743164, 0.7281979322433472, 0.7405746579170227, 0.7529513835906982, 0.765328049659729, 0.7777047753334045, 0.7900815010070801, 0.8024582266807556, 0.8148348927497864, 0.8272116184234619]}, "network.layer1.0.conv1_P_zeros": 0.9306098090277778, "network.layer1.0.conv1_S_zeros": 0.0, "network.layer1.0.conv1_Origin_zeros": 0.0, "network.layer1.0.conv2_mu": {"_type": "histogram", "values": [1, 0, 0, 1, 0, 0, 0, 0, 1, 0, 0, 0, 0, 0, 0, 0, 0, 0, 1, 1, 0, 0, 0, 0, 1, 0, 0, 1, 0, 1, 1, 0, 0, 0, 0, 0, 0, 0, 0, 0, 1, 0, 0, 0, 0, 0, 0, 0, 2, 0, 1, 0, 0, 0, 0, 0, 0, 0, 0, 0, 1, 0, 0, 1], "bins": [0.08860909938812256, 0.09972896426916122, 0.11084882915019989, 0.12196869403123856, 0.13308855891227722, 0.14420843124389648, 0.15532828867435455, 0.16644814610481262, 0.17756801843643188, 0.18868789076805115, 0.19980774819850922, 0.21092760562896729, 0.22204747796058655, 0.2331673502922058, 0.24428720772266388, 0.25540706515312195, 0.2665269374847412, 0.2776468098163605, 0.28876668214797974, 0.2998865246772766, 0.3110063970088959, 0.32212626934051514, 0.333246111869812, 0.3443659842014313, 0.35548585653305054, 0.3666057288646698, 0.37772560119628906, 0.38884544372558594, 0.3999653160572052, 0.41108518838882446, 0.42220503091812134, 0.4333249032497406, 0.44444477558135986, 0.4555646479129791, 0.4666845202445984, 0.47780436277389526, 0.4889242351055145, 0.5000441074371338, 0.5111639499664307, 0.5222838521003723, 0.5334036946296692, 0.5445235371589661, 0.5556434392929077, 0.5667632818222046, 0.5778831243515015, 0.5890030264854431, 0.60012286901474, 0.6112427711486816, 0.6223626136779785, 0.6334824562072754, 0.644602358341217, 0.6557222008705139, 0.6668421030044556, 0.6779619455337524, 0.6890817880630493, 0.700201690196991, 0.7113215327262878, 0.7224413752555847, 0.7335612773895264, 0.7446811199188232, 0.7558009624481201, 0.7669208645820618, 0.7780407071113586, 0.7891606092453003, 0.8002804517745972]}, "network.layer1.0.conv2_P_zeros": 0.9203830295138888, "network.layer1.0.conv2_S_zeros": 0.0, "network.layer1.0.conv2_Origin_zeros": 0.0, "network.layer1.1.conv1_mu": {"_type": "histogram", "values": [1, 0, 0, 1, 0, 0, 0, 0, 0, 0, 0, 0, 0, 0, 0, 0, 0, 0, 0, 0, 0, 0, 0, 1, 0, 0, 0, 0, 0, 0, 0, 0, 0, 1, 1, 1, 1, 0, 0, 0, 1, 2, 0, 0, 0, 0, 1, 0, 0, 0, 1, 1, 0, 0, 0, 0, 0, 0, 0, 1, 0, 0, 0, 1], "bins": [0.12290531396865845, 0.13582457602024078, 0.14874383807182312, 0.16166308522224426, 0.1745823472738266, 0.18750160932540894, 0.20042087137699127, 0.2133401334285736, 0.22625938057899475, 0.2391786426305771, 0.2520979046821594, 0.26501715183258057, 0.2779364287853241, 0.29085567593574524, 0.30377495288848877, 0.3166942000389099, 0.32961344718933105, 0.3425327241420746, 0.3554519712924957, 0.36837124824523926, 0.3812904953956604, 0.39420977234840393, 0.4071290194988251, 0.4200482666492462, 0.43296754360198975, 0.4458867907524109, 0.4588060677051544, 0.47172531485557556, 0.4846445620059967, 0.49756383895874023, 0.5104830861091614, 0.5234023332595825, 0.5363216400146484, 0.5492408871650696, 0.5621601343154907, 0.5750793814659119, 0.587998628616333, 0.6009179353713989, 0.6138371825218201, 0.6267564296722412, 0.6396756768226624, 0.6525949239730835, 0.6655142307281494, 0.6784334778785706, 0.6913527250289917, 0.7042719721794128, 0.717191219329834, 0.7301105260848999, 0.743029773235321, 0.7559490203857422, 0.7688682675361633, 0.7817875146865845, 0.7947068214416504, 0.8076260685920715, 0.8205453157424927, 0.8334645628929138, 0.846383810043335, 0.8593031167984009, 0.872222363948822, 0.8851416110992432, 0.8980608582496643, 0.9109801054000854, 0.9238994121551514, 0.9368186593055725, 0.9497379064559937]}, "network.layer1.1.conv1_P_zeros": 0.9195421006944444, "network.layer1.1.conv1_S_zeros": 0.0, "network.layer1.1.conv1_Origin_zeros": 0.0, "network.layer1.1.conv2_mu": {"_type": "histogram", "values": [1, 1, 0, 0, 1, 0, 0, 0, 1, 0, 0, 0, 0, 0, 0, 0, 0, 0, 0, 0, 0, 0, 1, 0, 0, 0, 0, 0, 0, 0, 0, 0, 1, 0, 0, 0, 0, 0, 1, 0, 0, 1, 0, 0, 0, 0, 0, 2, 0, 0, 0, 0, 0, 1, 1, 0, 1, 0, 0, 0, 0, 0, 1, 1], "bins": [0.02104133367538452, 0.036128636449575424, 0.05121593922376633, 0.06630323827266693, 0.08139054477214813, 0.09647784382104874, 0.11156514286994934, 0.12665244936943054, 0.14173975586891174, 0.15682704746723175, 0.17191435396671295, 0.18700166046619415, 0.20208895206451416, 0.21717625856399536, 0.23226356506347656, 0.24735085666179657, 0.26243817806243896, 0.2775254547595978, 0.292612761259079, 0.3077000677585602, 0.3227873742580414, 0.3378746807575226, 0.3529619872570038, 0.3680492639541626, 0.3831365704536438, 0.398223876953125, 0.4133111834526062, 0.4283984899520874, 0.4434857964515686, 0.4585730731487274, 0.4736603796482086, 0.4887476861476898, 0.5038349628448486, 0.5189222693443298, 0.534009575843811, 0.5490968823432922, 0.5641841888427734, 0.5792714953422546, 0.5943588018417358, 0.609446108341217, 0.6245334148406982, 0.6396207213401794, 0.6547080278396606, 0.6697953343391418, 0.684882640838623, 0.6999698877334595, 0.7150571942329407, 0.7301445007324219, 0.7452318072319031, 0.7603191137313843, 0.7754064202308655, 0.7904937267303467, 0.8055810332298279, 0.8206683397293091, 0.8357556462287903, 0.8508429527282715, 0.8659302592277527, 0.8810175657272339, 0.8961048126220703, 0.9111921191215515, 0.9262794256210327, 0.9413667321205139, 0.9564540386199951, 0.9715413451194763, 0.9866286516189575]}, "network.layer1.1.conv2_P_zeros": 0.9021809895833334, "network.layer1.1.conv2_S_zeros": 0.0, "network.layer1.1.conv2_Origin_zeros": 0.0, "network.layer2.0.conv1_mu": {"_type": "histogram", "values": [1, 0, 0, 0, 0, 0, 0, 0, 0, 0, 0, 0, 0, 0, 0, 1, 0, 1, 1, 0, 0, 0, 1, 0, 0, 0, 0, 0, 0, 0, 2, 0, 0, 0, 0, 1, 0, 0, 0, 1, 0, 0, 0, 1, 0, 0, 0, 0, 0, 0, 0, 1, 0, 1, 0, 0, 1, 0, 0, 0, 0, 0, 1, 1], "bins": [0.022020339965820312, 0.03712276741862297, 0.05222519487142563, 0.06732761859893799, 0.08243004977703094, 0.0975324809551239, 0.11263490468263626, 0.12773732841014862, 0.14283975958824158, 0.15794219076633453, 0.1730446219444275, 0.18814703822135925, 0.2032494693994522, 0.21835190057754517, 0.23345431685447693, 0.24855674803256989, 0.26365917921066284, 0.2787615954875946, 0.29386404156684875, 0.3089664578437805, 0.32406890392303467, 0.33917132019996643, 0.3542737364768982, 0.36937618255615234, 0.3844785988330841, 0.39958101511001587, 0.41468346118927, 0.4297858774662018, 0.44488829374313354, 0.4599907398223877, 0.47509315609931946, 0.4901956021785736, 0.5052980184555054, 0.5204004645347595, 0.5355028510093689, 0.550605297088623, 0.5657077431678772, 0.5808101296424866, 0.5959125757217407, 0.6110150218009949, 0.626117467880249, 0.6412198543548584, 0.6563223004341125, 0.6714247465133667, 0.6865271329879761, 0.7016295790672302, 0.7167320251464844, 0.7318344116210938, 0.7469368577003479, 0.762039303779602, 0.7771416902542114, 0.7922441363334656, 0.8073465824127197, 0.8224489688873291, 0.8375514149665833, 0.8526538610458374, 0.8677562475204468, 0.8828586935997009, 0.8979611396789551, 0.9130635857582092, 0.9281659722328186, 0.9432684183120728, 0.9583708643913269, 0.9734732508659363, 0.9885756969451904]}, "network.layer2.0.conv1_P_zeros": 0.9092068142361112, "network.layer2.0.conv1_S_zeros": 0.0, "network.layer2.0.conv1_Origin_zeros": 0.0, "network.layer2.0.conv2_mu": {"_type": "histogram", "values": [1, 0, 0, 1, 0, 0, 1, 0, 0, 0, 1, 0, 0, 0, 0, 1, 0, 0, 1, 0, 0, 0, 1, 0, 0, 0, 1, 1, 1, 1, 0, 0, 0, 0, 0, 0, 0, 0, 1, 0, 0, 0, 0, 0, 0, 0, 0, 0, 0, 0, 0, 0, 1, 0, 0, 0, 0, 1, 0, 0, 0, 0, 0, 1], "bins": [0.029043853282928467, 0.0429721474647522, 0.056900445371866226, 0.07082874327898026, 0.08475703746080399, 0.09868533164262772, 0.11261363327503204, 0.12654192745685577, 0.1404702216386795, 0.15439851582050323, 0.16832681000232697, 0.1822551041841507, 0.19618341326713562, 0.21011170744895935, 0.22404000163078308, 0.2379682958126068, 0.25189658999443054, 0.2658248841762543, 0.279753178358078, 0.29368147253990173, 0.30760976672172546, 0.3215380609035492, 0.3354663550853729, 0.34939464926719666, 0.3633229732513428, 0.3772512674331665, 0.39117956161499023, 0.40510785579681396, 0.4190361499786377, 0.4329644441604614, 0.44689273834228516, 0.4608210325241089, 0.4747493267059326, 0.48867762088775635, 0.5026059150695801, 0.5165342092514038, 0.5304625034332275, 0.5443907976150513, 0.558319091796875, 0.5722473859786987, 0.5861756801605225, 0.6001039743423462, 0.6140322685241699, 0.6279605627059937, 0.6418888568878174, 0.6558171510696411, 0.6697454452514648, 0.6836737394332886, 0.6976020336151123, 0.7115303874015808, 0.7254586815834045, 0.7393869757652283, 0.753315269947052, 0.7672435641288757, 0.7811718583106995, 0.7951001524925232, 0.8090284466743469, 0.8229567408561707, 0.8368850350379944, 0.8508133292198181, 0.8647416234016418, 0.8786699175834656, 0.8925982117652893, 0.906526505947113, 0.9204548001289368]}, "network.layer2.0.conv2_P_zeros": 0.9380696614583334, "network.layer2.0.conv2_S_zeros": 0.0, "network.layer2.0.conv2_Origin_zeros": 0.0, "network.layer2.0.downsample.0_mu": {"_type": "histogram", "values": [1, 0, 0, 1, 0, 1, 0, 0, 1, 0, 0, 0, 1, 0, 0, 1, 1, 0, 0, 0, 0, 0, 0, 0, 0, 1, 0, 1, 0, 0, 0, 0, 1, 0, 1, 0, 0, 0, 0, 0, 0, 0, 0, 0, 0, 0, 0, 0, 0, 0, 0, 0, 0, 0, 1, 1, 0, 0, 0, 0, 0, 0, 0, 2], "bins": [0.018237650394439697, 0.03167317435145378, 0.045108698308467865, 0.05854422226548195, 0.07197974622249603, 0.08541527390480042, 0.0988507941365242, 0.11228631436824799, 0.12572184205055237, 0.13915736973285675, 0.15259289741516113, 0.16602841019630432, 0.1794639378786087, 0.19289946556091309, 0.20633497834205627, 0.21977050602436066, 0.23320603370666504, 0.24664156138896942, 0.2600770890712738, 0.273512601852417, 0.28694814443588257, 0.30038365721702576, 0.31381916999816895, 0.3272547125816345, 0.3406902253627777, 0.3541257381439209, 0.3675612807273865, 0.38099679350852966, 0.39443230628967285, 0.4078678488731384, 0.4213033616542816, 0.4347389042377472, 0.4481744170188904, 0.46160992980003357, 0.47504547238349915, 0.48848098516464233, 0.5019165277481079, 0.5153520107269287, 0.5287875533103943, 0.5422230958938599, 0.5556585788726807, 0.5690941214561462, 0.5825296640396118, 0.5959652066230774, 0.6094006896018982, 0.6228362321853638, 0.6362717747688293, 0.6497072577476501, 0.6631428003311157, 0.6765783429145813, 0.6900138258934021, 0.7034493684768677, 0.7168849110603333, 0.730320394039154, 0.7437559366226196, 0.7571914792060852, 0.7706270217895508, 0.7840625047683716, 0.7974980473518372, 0.8109335899353027, 0.8243690729141235, 0.8378046154975891, 0.8512401580810547, 0.8646756410598755, 0.8781111836433411]}, "network.layer2.0.downsample.0_P_zeros": 0.6990966796875, "network.layer2.0.downsample.0_S_zeros": 0.0, "network.layer2.0.downsample.0_Origin_zeros": 0.0, "network.layer2.1.conv1_mu": {"_type": "histogram", "values": [3, 0, 0, 0, 0, 0, 0, 0, 0, 0, 0, 0, 0, 0, 0, 0, 0, 0, 0, 0, 0, 0, 0, 0, 0, 0, 1, 0, 0, 0, 0, 0, 0, 0, 0, 1, 0, 0, 1, 0, 1, 0, 0, 0, 0, 2, 0, 0, 0, 0, 1, 1, 1, 0, 0, 0, 0, 0, 1, 0, 0, 1, 0, 1], "bins": [0.019141316413879395, 0.03406587615609169, 0.048990435898303986, 0.06391499191522598, 0.07883955538272858, 0.09376411139965057, 0.10868866741657257, 0.12361323088407516, 0.13853779435157776, 0.15346235036849976, 0.16838690638542175, 0.18331146240234375, 0.19823601841926575, 0.21316057443618774, 0.22808514535427094, 0.24300970137119293, 0.2579342722892761, 0.2728588283061981, 0.2877833843231201, 0.3027079403400421, 0.3176324963569641, 0.3325570523738861, 0.3474816083908081, 0.3624061644077301, 0.3773307204246521, 0.3922552764415741, 0.4071798324584961, 0.4221044182777405, 0.4370289742946625, 0.4519535303115845, 0.46687808632850647, 0.48180264234542847, 0.49672719836235046, 0.5116517543792725, 0.5265763401985168, 0.5415008664131165, 0.5564254522323608, 0.5713499784469604, 0.5862745642662048, 0.6011990904808044, 0.6161236763000488, 0.6310482025146484, 0.6459727883338928, 0.6608973741531372, 0.6758219003677368, 0.6907464861869812, 0.7056710124015808, 0.7205955982208252, 0.7355201244354248, 0.7504447102546692, 0.7653692364692688, 0.7802938222885132, 0.7952183485031128, 0.8101429343223572, 0.8250675201416016, 0.8399920463562012, 0.8549166321754456, 0.8698411583900452, 0.8847657442092896, 0.8996902704238892, 0.9146148562431335, 0.9295393824577332, 0.9444639682769775, 0.9593884944915771, 0.9743130803108215]}, "network.layer2.1.conv1_P_zeros": 0.9474148220486112, "network.layer2.1.conv1_S_zeros": 0.0, "network.layer2.1.conv1_Origin_zeros": 0.0, "network.layer2.1.conv2_mu": {"_type": "histogram", "values": [1, 1, 0, 0, 0, 0, 0, 0, 0, 0, 0, 0, 0, 0, 0, 1, 0, 1, 0, 0, 0, 0, 0, 0, 0, 0, 0, 0, 0, 0, 0, 0, 0, 0, 1, 0, 1, 0, 0, 0, 0, 0, 0, 0, 2, 0, 1, 1, 1, 0, 0, 0, 0, 1, 0, 0, 2, 0, 0, 0, 0, 0, 0, 1], "bins": [0.06727403402328491, 0.08181346952915192, 0.09635290503501892, 0.11089234054088593, 0.12543177604675293, 0.13997121155261993, 0.15451064705848694, 0.16905008256435394, 0.18358951807022095, 0.19812895357608795, 0.21266838908195496, 0.22720782458782196, 0.24174726009368896, 0.2562866806983948, 0.270826131105423, 0.28536558151245117, 0.299905002117157, 0.3144444227218628, 0.328983873128891, 0.3435233235359192, 0.358062744140625, 0.3726021647453308, 0.387141615152359, 0.4016810655593872, 0.416220486164093, 0.43075990676879883, 0.445299357175827, 0.4598388075828552, 0.47437822818756104, 0.48891764879226685, 0.5034570693969727, 0.5179965496063232, 0.532535970211029, 0.5470753908157349, 0.5616148710250854, 0.5761542916297913, 0.5906937122344971, 0.6052331328392029, 0.6197725534439087, 0.6343120336532593, 0.6488514542579651, 0.6633908748626709, 0.6779303550720215, 0.6924697756767273, 0.7070091962814331, 0.7215486168861389, 0.7360880374908447, 0.7506275177001953, 0.7651669383049011, 0.7797063589096069, 0.7942458391189575, 0.8087852597236633, 0.8233246803283691, 0.837864100933075, 0.8524035215377808, 0.8669430017471313, 0.8814824223518372, 0.896021842956543, 0.9105613231658936, 0.9251007437705994, 0.9396401643753052, 0.954179584980011, 0.9687190055847168, 0.9832584857940674, 0.9977979063987732]}, "network.layer2.1.conv2_P_zeros": 0.9623006184895834, "network.layer2.1.conv2_S_zeros": 0.0, "network.layer2.1.conv2_Origin_zeros": 0.0, "network.layer3.0.conv1_mu": {"_type": "histogram", "values": [2, 0, 2, 0, 0, 0, 0, 0, 0, 0, 1, 0, 0, 0, 0, 0, 0, 0, 0, 1, 0, 0, 1, 0, 0, 0, 0, 0, 0, 0, 0, 1, 0, 0, 0, 0, 0, 1, 0, 0, 0, 0, 1, 0, 0, 0, 0, 1, 1, 0, 0, 0, 0, 0, 0, 0, 0, 0, 0, 0, 0, 1, 0, 2], "bins": [0.01890617609024048, 0.03384651988744736, 0.048786863684654236, 0.06372720748186111, 0.078667551279068, 0.09360789507627487, 0.10854823887348175, 0.12348858267068863, 0.1384289264678955, 0.15336927771568298, 0.16830961406230927, 0.18324995040893555, 0.19819030165672302, 0.2131306529045105, 0.22807098925113678, 0.24301132559776306, 0.25795167684555054, 0.272892028093338, 0.2878323793411255, 0.3027727007865906, 0.31771305203437805, 0.3326534032821655, 0.3475937247276306, 0.3625340759754181, 0.37747442722320557, 0.39241477847099304, 0.4073551297187805, 0.4222954511642456, 0.4372358024120331, 0.45217615365982056, 0.46711647510528564, 0.4820568263530731, 0.4969971776008606, 0.5119374990463257, 0.5268778800964355, 0.5418182015419006, 0.5567585229873657, 0.5716989040374756, 0.5866392254829407, 0.6015796065330505, 0.6165199279785156, 0.6314602494239807, 0.6464006304740906, 0.6613409519195557, 0.6762813329696655, 0.6912216544151306, 0.7061619758605957, 0.7211023569107056, 0.7360426783561707, 0.7509829998016357, 0.7659233808517456, 0.7808637022972107, 0.7958040237426758, 0.8107444047927856, 0.8256847262382507, 0.8406251072883606, 0.8555654287338257, 0.8705057501792908, 0.8854461312294006, 0.9003864526748657, 0.9153268337249756, 0.9302671551704407, 0.9452074766159058, 0.9601478576660156, 0.9750881791114807]}, "network.layer3.0.conv1_P_zeros": 0.9568311903211806, "network.layer3.0.conv1_S_zeros": 0.0, "network.layer3.0.conv1_Origin_zeros": 0.0, "network.layer3.0.conv2_mu": {"_type": "histogram", "values": [3, 0, 0, 0, 0, 0, 0, 0, 0, 0, 0, 0, 0, 0, 1, 1, 0, 0, 0, 0, 0, 0, 0, 0, 0, 0, 0, 0, 0, 1, 0, 0, 0, 1, 0, 0, 1, 0, 0, 0, 0, 0, 0, 2, 1, 0, 0, 0, 0, 0, 0, 1, 0, 1, 0, 0, 0, 0, 0, 0, 0, 0, 0, 2], "bins": [0.005894005298614502, 0.02116994559764862, 0.03644588589668274, 0.05172182247042656, 0.06699776649475098, 0.0822736993432045, 0.09754963964223862, 0.11282557994127274, 0.12810152769088745, 0.14337745308876038, 0.1586533933877945, 0.1739293336868286, 0.18920527398586273, 0.20448121428489685, 0.21975715458393097, 0.2350330948829651, 0.2503090500831604, 0.2655849754810333, 0.28086090087890625, 0.29613685607910156, 0.3114127814769745, 0.3266887366771698, 0.3419646620750427, 0.35724061727523804, 0.37251654267311096, 0.3877924978733063, 0.4030684232711792, 0.4183443784713745, 0.43362030386924744, 0.44889625906944275, 0.4641721844673157, 0.479448139667511, 0.4947240650653839, 0.5099999904632568, 0.5252759456634521, 0.5405519008636475, 0.555827796459198, 0.5711037516593933, 0.5863797068595886, 0.6016556620597839, 0.6169315576553345, 0.6322075128555298, 0.6474834680557251, 0.6627594232559204, 0.678035318851471, 0.6933112740516663, 0.7085872292518616, 0.7238631844520569, 0.7391390800476074, 0.7544150352478027, 0.769690990447998, 0.7849668860435486, 0.8002428412437439, 0.8155187964439392, 0.8307947516441345, 0.8460706472396851, 0.8613466024398804, 0.8766225576400757, 0.891898512840271, 0.9071744084358215, 0.9224503636360168, 0.9377263188362122, 0.9530022740364075, 0.968278169631958, 0.9835541248321533]}, "network.layer3.0.conv2_P_zeros": 0.9725867377387153, "network.layer3.0.conv2_S_zeros": 0.0, "network.layer3.0.conv2_Origin_zeros": 0.0, "network.layer3.0.downsample.0_mu": {"_type": "histogram", "values": [1, 0, 0, 0, 0, 1, 0, 0, 0, 1, 0, 0, 0, 0, 0, 0, 0, 0, 1, 0, 1, 0, 0, 0, 0, 0, 0, 0, 0, 0, 0, 0, 0, 0, 0, 1, 0, 0, 1, 0, 0, 0, 1, 1, 0, 0, 1, 1, 0, 0, 0, 0, 0, 0, 0, 0, 0, 0, 0, 0, 2, 0, 1, 1], "bins": [0.05145764350891113, 0.0662415400147438, 0.08102542906999588, 0.09580932557582855, 0.11059321463108063, 0.1253771185874939, 0.14016100764274597, 0.15494489669799805, 0.16972878575325012, 0.1845126897096634, 0.19929657876491547, 0.21408046782016754, 0.2288643717765808, 0.24364826083183289, 0.25843214988708496, 0.27321603894233704, 0.2879999279975891, 0.3027838468551636, 0.31756773591041565, 0.3323516249656677, 0.3471355140209198, 0.3619194030761719, 0.37670329213142395, 0.3914872109889984, 0.4062711000442505, 0.42105498909950256, 0.43583887815475464, 0.4506227672100067, 0.4654066562652588, 0.48019057512283325, 0.4949744641780853, 0.5097583532333374, 0.5245422124862671, 0.5393261313438416, 0.554110050201416, 0.5688939094543457, 0.5836778283119202, 0.5984616875648499, 0.6132456064224243, 0.6280295252799988, 0.6428133845329285, 0.6575973033905029, 0.6723811626434326, 0.6871650815010071, 0.7019489407539368, 0.7167328596115112, 0.7315167784690857, 0.7463006377220154, 0.7610845565795898, 0.7758684158325195, 0.790652334690094, 0.8054361939430237, 0.8202201128005981, 0.8350040316581726, 0.8497878909111023, 0.8645718097686768, 0.8793556690216064, 0.8941395878791809, 0.9089235067367554, 0.9237073659896851, 0.9384912848472595, 0.9532751441001892, 0.9680590629577637, 0.9828429222106934, 0.9976268410682678]}, "network.layer3.0.downsample.0_P_zeros": 0.879852294921875, "network.layer3.0.downsample.0_S_zeros": 0.0, "network.layer3.0.downsample.0_Origin_zeros": 0.0, "network.layer3.1.conv1_mu": {"_type": "histogram", "values": [4, 0, 0, 0, 0, 0, 0, 0, 0, 0, 0, 1, 0, 0, 0, 0, 0, 0, 0, 1, 0, 0, 1, 0, 0, 0, 0, 0, 0, 0, 2, 0, 0, 0, 0, 0, 0, 0, 0, 0, 0, 1, 0, 0, 0, 1, 0, 0, 0, 0, 0, 1, 0, 0, 0, 0, 0, 1, 0, 0, 0, 0, 0, 2], "bins": [0.03588986396789551, 0.050357360392808914, 0.06482485681772232, 0.07929234951734543, 0.09375984966754913, 0.10822734236717224, 0.12269483506679535, 0.13716232776641846, 0.15162983536720276, 0.16609732806682587, 0.18056482076644897, 0.19503231346607208, 0.2094998061656952, 0.2239672988653183, 0.2384348064661026, 0.2529022991657257, 0.26736980676651, 0.2818372845649719, 0.2963047921657562, 0.31077226996421814, 0.32523977756500244, 0.33970725536346436, 0.35417476296424866, 0.36864227056503296, 0.3831097483634949, 0.3975772559642792, 0.4120447337627411, 0.4265122413635254, 0.4409797489643097, 0.4554472267627716, 0.4699147343635559, 0.4843822121620178, 0.4988497197628021, 0.5133172273635864, 0.5277847051620483, 0.5422521829605103, 0.5567197203636169, 0.5711871981620789, 0.5856546759605408, 0.6001222133636475, 0.6145896911621094, 0.6290571689605713, 0.6435246467590332, 0.6579921841621399, 0.6724596619606018, 0.6869271397590637, 0.7013946771621704, 0.7158621549606323, 0.7303296327590942, 0.7447971701622009, 0.7592646479606628, 0.7737321257591248, 0.7881996035575867, 0.8026671409606934, 0.8171346187591553, 0.8316020965576172, 0.8460696339607239, 0.8605371117591858, 0.8750045895576477, 0.8894721269607544, 0.9039396047592163, 0.9184070825576782, 0.9328745603561401, 0.9473420977592468, 0.9618095755577087]}, "network.layer3.1.conv1_P_zeros": 0.9768252902560763, "network.layer3.1.conv1_S_zeros": 0.0, "network.layer3.1.conv1_Origin_zeros": 0.0, "network.layer3.1.conv2_mu": {"_type": "histogram", "values": [2, 0, 0, 0, 0, 1, 0, 0, 0, 0, 0, 0, 0, 0, 0, 0, 0, 1, 1, 0, 1, 0, 0, 1, 0, 0, 0, 0, 1, 0, 0, 0, 1, 0, 0, 0, 1, 0, 0, 0, 1, 0, 0, 0, 0, 0, 0, 0, 1, 0, 0, 0, 0, 0, 0, 1, 0, 0, 0, 0, 1, 0, 0, 1], "bins": [0.01385354995727539, 0.028322942554950714, 0.04279233515262604, 0.05726172775030136, 0.07173112034797668, 0.08620051294565201, 0.10066990554332733, 0.11513929814100266, 0.12960869073867798, 0.1440780758857727, 0.15854747593402863, 0.17301687598228455, 0.18748626112937927, 0.201955646276474, 0.21642504632472992, 0.23089444637298584, 0.24536383152008057, 0.2598332166671753, 0.27430260181427, 0.28877201676368713, 0.30324140191078186, 0.3177107870578766, 0.3321802020072937, 0.3466495871543884, 0.36111897230148315, 0.3755883574485779, 0.3900577425956726, 0.4045271575450897, 0.41899654269218445, 0.4334659278392792, 0.4479353427886963, 0.462404727935791, 0.47687411308288574, 0.49134349822998047, 0.5058128833770752, 0.5202822685241699, 0.5347516536712646, 0.5492210984230042, 0.5636904835700989, 0.5781598687171936, 0.5926292538642883, 0.6070986390113831, 0.6215680241584778, 0.6360374093055725, 0.650506854057312, 0.6649762392044067, 0.6794456243515015, 0.6939150094985962, 0.7083843946456909, 0.7228537797927856, 0.7373231649398804, 0.7517925500869751, 0.7662619352340698, 0.7807313799858093, 0.795200765132904, 0.8096701502799988, 0.8241395354270935, 0.8386089205741882, 0.853078305721283, 0.8675476908683777, 0.8820171356201172, 0.8964865207672119, 0.9109559059143066, 0.9254252910614014, 0.9398946762084961]}, "network.layer3.1.conv2_P_zeros": 0.9930691189236112, "network.layer3.1.conv2_S_zeros": 0.0, "network.layer3.1.conv2_Origin_zeros": 0.0, "network.layer4.0.conv1_mu": {"_type": "histogram", "values": [1, 1, 1, 0, 0, 0, 1, 0, 0, 0, 0, 0, 0, 0, 1, 0, 0, 0, 0, 0, 0, 0, 0, 1, 0, 0, 0, 0, 0, 0, 1, 0, 2, 1, 0, 0, 0, 0, 0, 0, 0, 0, 0, 0, 0, 0, 0, 0, 0, 0, 0, 1, 1, 0, 0, 0, 0, 0, 1, 0, 0, 0, 1, 1], "bins": [0.014284253120422363, 0.027896221727132797, 0.04150819033384323, 0.05512015521526337, 0.0687321275472641, 0.08234409242868423, 0.09595605731010437, 0.1095680296421051, 0.12317999452352524, 0.13679195940494537, 0.1504039317369461, 0.16401590406894684, 0.17762786149978638, 0.1912398338317871, 0.20485180616378784, 0.21846376359462738, 0.2320757359266281, 0.24568770825862885, 0.2592996656894684, 0.2729116380214691, 0.28652361035346985, 0.3001355826854706, 0.3137475550174713, 0.32735949754714966, 0.3409714698791504, 0.3545834422111511, 0.36819541454315186, 0.3818073868751526, 0.3954193592071533, 0.40903130173683167, 0.4226432740688324, 0.43625524640083313, 0.44986721873283386, 0.4634791910648346, 0.4770911633968353, 0.49070313572883606, 0.5043150782585144, 0.5179270505905151, 0.5315390229225159, 0.5451509952545166, 0.5587629675865173, 0.5723749399185181, 0.5859869122505188, 0.5995988845825195, 0.6132108569145203, 0.6268227696418762, 0.640434741973877, 0.6540467143058777, 0.6676586866378784, 0.6812706589698792, 0.6948826313018799, 0.7084946036338806, 0.7221065759658813, 0.7357185482978821, 0.7493305206298828, 0.7629424929618835, 0.7765544652938843, 0.790166437625885, 0.803778350353241, 0.8173903226852417, 0.8310022950172424, 0.8446142673492432, 0.8582262396812439, 0.8718382120132446, 0.8854501843452454]}, "network.layer4.0.conv1_P_zeros": 0.9996363321940104, "network.layer4.0.conv1_S_zeros": 0.0, "network.layer4.0.conv1_Origin_zeros": 0.0, "network.layer4.0.conv2_mu": {"_type": "histogram", "values": [1, 1, 0, 0, 0, 1, 0, 0, 0, 0, 1, 0, 0, 0, 1, 0, 0, 1, 0, 0, 0, 0, 0, 0, 0, 0, 0, 0, 0, 0, 1, 2, 0, 0, 0, 1, 0, 0, 1, 0, 0, 0, 1, 0, 0, 0, 0, 0, 0, 0, 0, 0, 0, 0, 0, 0, 0, 0, 1, 0, 0, 0, 1, 1], "bins": [0.08680474758148193, 0.0998942106962204, 0.11298367381095886, 0.12607313692569733, 0.1391626000404358, 0.15225206315517426, 0.16534152626991272, 0.17843098938465118, 0.19152045249938965, 0.20460990071296692, 0.21769936382770538, 0.23078882694244385, 0.2438782900571823, 0.2569677531719208, 0.27005723118782043, 0.2831466794013977, 0.29623615741729736, 0.30932560563087463, 0.3224150538444519, 0.33550453186035156, 0.34859398007392883, 0.3616834580898285, 0.37477290630340576, 0.3878623843193054, 0.4009518325328827, 0.41404131054878235, 0.4271307587623596, 0.4402202367782593, 0.45330968499183655, 0.4663991630077362, 0.4794886112213135, 0.49257808923721313, 0.5056675672531128, 0.5187569856643677, 0.5318464636802673, 0.544935941696167, 0.5580253601074219, 0.5711148381233215, 0.5842043161392212, 0.5972937941551208, 0.6103832125663757, 0.6234726905822754, 0.636562168598175, 0.6496516466140747, 0.6627410650253296, 0.6758305430412292, 0.6889200210571289, 0.7020094990730286, 0.7150989174842834, 0.7281883955001831, 0.7412778735160828, 0.7543672919273376, 0.7674567699432373, 0.780546247959137, 0.7936357259750366, 0.8067251443862915, 0.8198146224021912, 0.8329041004180908, 0.8459935784339905, 0.8590829968452454, 0.872172474861145, 0.8852619528770447, 0.8983514308929443, 0.9114408493041992, 0.9245303273200989]}, "network.layer4.0.conv2_P_zeros": 0.9999970330132378, "network.layer4.0.conv2_S_zeros": 0.0, "network.layer4.0.conv2_Origin_zeros": 0.0, "network.layer4.0.downsample.0_mu": {"_type": "histogram", "values": [1, 0, 0, 0, 1, 0, 1, 0, 0, 0, 0, 1, 0, 1, 0, 0, 0, 0, 0, 0, 0, 0, 0, 0, 0, 0, 0, 0, 0, 1, 0, 0, 1, 0, 0, 0, 0, 0, 0, 0, 0, 1, 0, 1, 0, 0, 1, 0, 0, 1, 1, 0, 0, 0, 1, 0, 0, 0, 0, 0, 1, 0, 0, 1], "bins": [0.020935654640197754, 0.03557189553976059, 0.050208136439323425, 0.06484437733888626, 0.0794806182384491, 0.09411685168743134, 0.10875309258699417, 0.123389333486557, 0.13802558183670044, 0.15266181528568268, 0.16729804873466492, 0.18193429708480835, 0.1965705305337906, 0.21120677888393402, 0.22584301233291626, 0.2404792606830597, 0.2551155090332031, 0.26975172758102417, 0.2843879759311676, 0.29902422428131104, 0.3136604428291321, 0.3282966911792755, 0.34293293952941895, 0.3575691878795624, 0.3722054064273834, 0.38684165477752686, 0.4014779031276703, 0.41611412167549133, 0.43075037002563477, 0.4453866183757782, 0.46002286672592163, 0.4746590852737427, 0.4892953336238861, 0.5039315819740295, 0.5185678005218506, 0.5332040786743164, 0.5478402972221375, 0.5624765157699585, 0.5771127939224243, 0.5917490124702454, 0.6063852310180664, 0.6210215091705322, 0.6356577277183533, 0.6502939462661743, 0.6649302244186401, 0.6795664429664612, 0.694202721118927, 0.708838939666748, 0.7234751582145691, 0.7381114363670349, 0.752747654914856, 0.767383873462677, 0.7820201516151428, 0.7966563701629639, 0.8112925887107849, 0.8259288668632507, 0.8405650854110718, 0.8552013039588928, 0.8698375821113586, 0.8844738006591797, 0.8991100788116455, 0.9137462973594666, 0.9283825159072876, 0.9430187940597534, 0.9576550126075745]}, "network.layer4.0.downsample.0_P_zeros": 0.99847412109375, "network.layer4.0.downsample.0_S_zeros": 0.0, "network.layer4.0.downsample.0_Origin_zeros": 0.0, "network.layer4.1.conv1_mu": {"_type": "histogram", "values": [1, 0, 0, 0, 2, 0, 0, 0, 0, 1, 0, 0, 1, 0, 1, 0, 0, 0, 1, 0, 0, 0, 0, 0, 0, 0, 0, 1, 0, 1, 1, 0, 0, 0, 0, 0, 0, 0, 1, 0, 0, 0, 0, 0, 0, 0, 0, 0, 0, 0, 1, 0, 1, 1, 0, 0, 0, 0, 0, 0, 0, 0, 0, 1], "bins": [0.011260807514190674, 0.025863591581583023, 0.04046637564897537, 0.05506915599107742, 0.06967194378376007, 0.08427472412586212, 0.09887750446796417, 0.11348029226064682, 0.12808308005332947, 0.14268586039543152, 0.15728864073753357, 0.17189142107963562, 0.18649420142173767, 0.20109698176383972, 0.21569977700710297, 0.23030255734920502, 0.24490533769130707, 0.2595081329345703, 0.27411091327667236, 0.2887136936187744, 0.30331647396087646, 0.3179192543029785, 0.33252203464508057, 0.3471248149871826, 0.36172759532928467, 0.3763303756713867, 0.39093315601348877, 0.4055359661579132, 0.42013874650001526, 0.4347415268421173, 0.44934430718421936, 0.4639470875263214, 0.47854986786842346, 0.4931526482105255, 0.50775545835495, 0.522358238697052, 0.536961019039154, 0.5515637993812561, 0.5661665797233582, 0.5807693600654602, 0.5953721404075623, 0.6099749207496643, 0.6245777010917664, 0.6391804814338684, 0.6537832617759705, 0.6683860421180725, 0.6829888224601746, 0.6975916028022766, 0.7121943831443787, 0.7267971634864807, 0.7413999438285828, 0.7560027241706848, 0.7706055045127869, 0.7852082848548889, 0.7998111248016357, 0.8144139051437378, 0.8290166854858398, 0.8436194658279419, 0.858222246170044, 0.872825026512146, 0.887427806854248, 0.9020305871963501, 0.9166333675384521, 0.9312361478805542, 0.9458389282226562]}, "network.layer4.1.conv1_P_zeros": 0.9999987284342448, "network.layer4.1.conv1_S_zeros": 0.0, "network.layer4.1.conv1_Origin_zeros": 0.0, "network.layer4.1.conv2_mu": {"_type": "histogram", "values": [1, 1, 0, 0, 0, 0, 0, 0, 1, 0, 0, 1, 0, 1, 0, 0, 0, 0, 0, 0, 0, 1, 0, 1, 0, 0, 0, 0, 0, 1, 0, 0, 0, 0, 0, 0, 0, 0, 0, 0, 0, 0, 0, 1, 0, 1, 0, 0, 0, 0, 0, 0, 1, 1, 0, 1, 0, 0, 0, 0, 1, 0, 0, 1], "bins": [0.09281283617019653, 0.10666252672672272, 0.1205122098326683, 0.1343618929386139, 0.14821158349514008, 0.16206127405166626, 0.17591096460819244, 0.18976065516471863, 0.20361033082008362, 0.2174600213766098, 0.231309711933136, 0.24515940248966217, 0.25900909304618835, 0.27285876870155334, 0.2867084741592407, 0.3005581498146057, 0.3144078254699707, 0.3282575309276581, 0.34210720658302307, 0.35595691204071045, 0.36980658769607544, 0.3836562931537628, 0.3975059688091278, 0.4113556444644928, 0.4252053499221802, 0.43905502557754517, 0.45290473103523254, 0.46675440669059753, 0.4806040823459625, 0.4944537878036499, 0.5083034634590149, 0.5221531391143799, 0.5360028743743896, 0.5498525500297546, 0.5637022256851196, 0.5775519013404846, 0.5914015769958496, 0.6052513122558594, 0.6191009879112244, 0.6329506635665894, 0.6468003392219543, 0.6606500148773193, 0.6744997501373291, 0.6883494257926941, 0.7021991014480591, 0.7160487771034241, 0.7298984527587891, 0.7437481880187988, 0.7575978636741638, 0.7714475393295288, 0.7852972149848938, 0.7991468906402588, 0.8129966259002686, 0.8268463015556335, 0.8406959772109985, 0.8545456528663635, 0.8683953285217285, 0.8822450637817383, 0.8960947394371033, 0.9099444150924683, 0.9237940907478333, 0.9376437664031982, 0.951493501663208, 0.965343177318573, 0.979192852973938]}, "network.layer4.1.conv2_P_zeros": 1.0, "network.layer4.1.conv2_S_zeros": 0.0, "network.layer4.1.conv2_Origin_zeros": 0.0, "network.fc_sparsity": 0.0, "_wandb": {"runtime": 19}}